fire_python/__init__.py
fire_python/fire_python.py
fire_python-0.42.dist-info/DESCRIPTION.rst
fire_python-0.42.dist-info/METADATA
fire_python-0.42.dist-info/RECORD
fire_python-0.42.dist-info/WHEEL
fire_python-0.42.dist-info/metadata.json
fire_python-0.42.dist-info/top_level.txt
