Metadata-Version: 2.0
Name: fire-python
Version: 0.42
Summary: Functional Inference and Reasoning Engine - Python
Home-page: https://public.git.erdc.dren.mil/rdchlarb/fire_python.git
Author: Aaron Byrd
Author-email: AaronRByrd@gmail.com
License: FIRE-Python is licensed under the GNU General Public License version 3, 2007. FIRE-Python may also be available under alternative licenses (multi licensing model). This is so that it may be sold or licensed for use in proprietary applications. If you wish to use or incorporate this program (or parts of it) into other software that does not meet the GNU General Public License conditions contact the author to discuss a licensing agreement.
Platform: UNKNOWN
